ALU.sv
module alu(
    input logic [3:0] A, 
    input logic [3:0] B,  
    input logic [3:0] alu_op,     
    output logic [3:0] alu_out    
);

// Lógica de la ALU
always_comb 
    case (alu_op)
        4'b0000: alu_out = A + B;               
        4'b1000: alu_out = A - B;             
        4'b0001: alu_out = A << B;         
        4'b0101: alu_out = A >> B;         
        4'b1101: alu_out = $signed(A) >>> B;
        4'b0010: alu_out = $signed(A) < $signed(B);  
        4'b0011: alu_out = A < B; 
        4'b0111: alu_out = A & B;              
        4'b0110: alu_out = A | B;               
        4'b0100: alu_out = A ^ B;         
        default: alu_out = 4'b0;               
    endcase

endmodule

ALU_tb.sv
module alu_tb;

  logic [3:0] A_tb = 0;
  logic [3:0] B_tb = 0;
  logic [3:0] alu_op_tb = 4'b0000;
  logic [3:0] alu_out_tb;

  alu alu1 (
    .A(A_tb),
    .B(B_tb),
    .alu_op(alu_op_tb),
    .alu_out(alu_out_tb)
  );

  initial begin
    $dumpfile("alu.vcd");
    $dumpvars(0, alu_tb);
    #20;
        // Pruebas 1: Suma
    alu_op_tb = 4'b0000; A_tb = 4'b0101; B_tb = 4'b1010; #20;    
    alu_op_tb = 4'b0000; A_tb = 4'b0001; B_tb = 4'b1010; #20;    
    alu_op_tb = 4'b0000; A_tb = 4'b1101; B_tb = 4'b1010; #20;
    alu_op_tb = 4'b0000; A_tb = 4'b0000; B_tb = 4'b1010; #20;

    // Pruebas 2: Resta
    alu_op_tb = 4'b1000; A_tb = 4'b0101; B_tb = 4'b1010; #20;
    alu_op_tb = 4'b1000; A_tb = 4'b0001; B_tb = 4'b1010; #20;
    alu_op_tb = 4'b1000; A_tb = 4'b0011; B_tb = 4'b1010; #20;
    alu_op_tb = 4'b1000; A_tb = 4'b0100; B_tb = 4'b1010; #20;
    
    // Pruebas 3: Corrimiento lógico a la izquierda
    alu_op_tb = 4'b0001; A_tb = 4'b0011; B_tb = 4'b0001; #20;
    alu_op_tb = 4'b0001; A_tb = 4'b0101; B_tb = 4'b0001; #20;
    alu_op_tb = 4'b0001; A_tb = 4'b0111; B_tb = 4'b0001; #20;
    alu_op_tb = 4'b0001; A_tb = 4'b0100; B_tb = 4'b0001; #20;
    
    // Pruebas 4: Corrimiento lógico a la derecha
    alu_op_tb = 4'b0101; A_tb = 4'b1000; B_tb = 4'b0010; #20;    
    alu_op_tb = 4'b0101; A_tb = 4'b1100; B_tb = 4'b0010; #20;
    alu_op_tb = 4'b0101; A_tb = 4'b0100; B_tb = 4'b0010; #20;
    alu_op_tb = 4'b0101; A_tb = 4'b1010; B_tb = 4'b0001; #20;
    
    // Prueba 5: Corrimiento aritmético a la derecha (con signo)
    alu_op_tb = 4'b1101; A_tb = 4'b1010; B_tb = 4'b0001; #20;
    alu_op_tb = 4'b1101; A_tb = 4'b0010; B_tb = 4'b0001; #20;
    alu_op_tb = 4'b1101; A_tb = 4'b1100; B_tb = 4'b0001; #20;
    alu_op_tb = 4'b1101; A_tb = 4'b0010; B_tb = 4'b0001; #20;
    
    // Prueba 6: Comparación < con signo
    alu_op_tb = 4'b0010; A_tb = 4'b1010; B_tb = 4'b0001; #20;
    alu_op_tb = 4'b0010; A_tb = 4'b1010; B_tb = 4'b0011; #20;
    alu_op_tb = 4'b0010; A_tb = 4'b1010; B_tb = 4'b1001; #20;
    alu_op_tb = 4'b0010; A_tb = 4'b1010; B_tb = 4'b1101; #20;
    
    // Prueba 7: Comparación < sin signo
    alu_op_tb = 4'b0011; A_tb = 4'b1001; B_tb = 4'b0110; #20;    
    alu_op_tb = 4'b0011; A_tb = 4'b1001; B_tb = 4'b1110; #20;
    alu_op_tb = 4'b0011; A_tb = 4'b1001; B_tb = 4'b0111; #20;
    alu_op_tb = 4'b0011; A_tb = 4'b1001; B_tb = 4'b1111; #20;

    // Prueba 8: AND
    alu_op_tb = 4'b0111; A_tb = 4'b1001; B_tb = 4'b1001; #20;
    alu_op_tb = 4'b0111; A_tb = 4'b1011; B_tb = 4'b1101; #20;
    alu_op_tb = 4'b0111; A_tb = 4'b1001; B_tb = 4'b0001; #20;
    alu_op_tb = 4'b0111; A_tb = 4'b0001; B_tb = 4'b1001; #20;
    
    // Prueba 9: OR
    alu_op_tb = 4'b0110; A_tb = 4'b1001; B_tb = 4'b1001; #20;
    alu_op_tb = 4'b0110; A_tb = 4'b1101; B_tb = 4'b1011; #20;
    alu_op_tb = 4'b0110; A_tb = 4'b1101; B_tb = 4'b1001; #2
    alu_op_tb = 4'b0110; A_tb = 4'b1011; B_tb = 4'b1001; #20;

    // Prueba 10: XOR
    alu_op_tb = 4'b0100; A_tb = 4'b1001; B_tb = 4'b1001; #20
    alu_op_tb = 4'b0100; A_tb = 4'b1011; B_tb = 4'b1001; #20
    alu_op_tb = 4'b0100; A_tb = 4'b1001; B_tb = 4'b1101; #20
    alu_op_tb = 4'b0100; A_tb = 4'b1011; B_tb = 4'b1101; #20;
    
    // Prueba 11: Valor predeterminado
    alu_op_tb = 4'b0000; A_tb = 4'b0000; B_tb = 4'b0000; #20;
    
    $finish;
  end
endmodule;

alu.vcd
$date
	Mon Oct 09 15:33:25 2023
$end
$version
	Icarus Verilog
$end
$timescale
	1s
$end
$scope module alu_tb $end
$var wire 4 ! alu_out_tb [3:0] $end
$var reg 4 " A_tb [3:0] $end
$var reg 4 # B_tb [3:0] $end
$var reg 4 $ alu_op_tb [3:0] $end
$scope module alu1 $end
$var wire 4 % A [3:0] $end
$var wire 4 & B [3:0] $end
$var wire 4 ' alu_op [3:0] $end
$var reg 4 ( alu_out [3:0] $end
$upscope $end
$upscope $end
$enddefinitions $end
$comment Show the parameter values. $end
$dumpall
$end
#0
$dumpvars
b0 (
b0 '
b0 &
b0 %
b0 $
b0 #
b0 "
b0 !
$end
#20
b1111 !
b1111 (
b1010 #
b1010 &
b101 "
b101 %
#40
b1011 !
b1011 (
b1 "
b1 %
#60
b111 !
b111 (
b1101 "
b1101 %
#80
b1010 !
b1010 (
b0 "
b0 %
#100
b1011 !
b1011 (
b101 "
b101 %
b1000 $
b1000 '
#120
b111 !
b111 (
b1 "
b1 %
#140
b1001 !
b1001 (
b11 "
b11 %
#160
b1010 !
b1010 (
b100 "
b100 %
#180
b110 !
b110 (
b1 #
b1 &
b11 "
b11 %
b1 $
b1 '
#200
b1010 !
b1010 (
b101 "
b101 %
#220
b1110 !
b1110 (
b111 "
b111 %
#240
b1000 !
b1000 (
b100 "
b100 %
#260
b10 !
b10 (
b10 #
b10 &
b1000 "
b1000 %
b101 $
b101 '
#280
b11 !
b11 (
b1100 "
b1100 %
#300
b1 !
b1 (
b100 "
b100 %
#320
b101 !
b101 (
b1 #
b1 &
b1010 "
b1010 %
#340
b1101 !
b1101 (
b1101 $
b1101 '
#360
b1 !
b1 (
b10 "
b10 %
#380
b1110 !
b1110 (
b1100 "
b1100 %
#400
b1 !
b1 (
b10 "
b10 %
#420
b1010 "
b1010 %
b10 $
b10 '
#440
b11 #
b11 &
#460
b0 !
b0 (
b1001 #
b1001 &
#480
b1 !
b1 (
b1101 #
b1101 &
#500
b0 !
b0 (
b110 #
b110 &
b1001 "
b1001 %
b11 $
b11 '
#520
b1 !
b1 (
b1110 #
b1110 &
#540
b0 !
b0 (
b111 #
b111 &
#560
b1 !
b1 (
b1111 #
b1111 &
#580
b1001 !
b1001 (
b1001 #
b1001 &
b111 $
b111 '
#600
b1101 #
b1101 &
b1011 "
b1011 %
#620
b1 !
b1 (
b1 #
b1 &
b1001 "
b1001 %
#640
b1001 #
b1001 &
b1 "
b1 %
#660
b1001 !
b1001 (
b1001 "
b1001 %
b110 $
b110 '
#680
b1111 !
b1111 (
b1011 #
b1011 &
b1101 "
b1101 %
#700
b1101 !
b1101 (
b1001 #
b1001 &
#720
b1011 !
b1011 (
b1011 "
b1011 %
#740
b0 !
b0 (
b1001 "
b1001 %
b100 $
b100 '
#760
b10 !
b10 (
b1011 "
b1011 %
#780
b100 !
b100 (
b1101 #
b1101 &
b1001 "
b1001 %
#800
b110 !
b110 (
b1011 "
b1011 %
#820
b0 !
b0 (
b0 #
b0 &
b0 "
b0 %
b0 $
b0 '
